Workbook

Sheet START HERE
B2: DEBT PAYOFF PLANNER
B4: Snowball or Avalanche — see your debt-free date either way.
B6: HOW TO USE
B7: 1. 'My Debts' tab: list every debt in the yellow cells (up to 10).
B8: 2. Enter your monthly extra payment in the yellow cell at the top.
B9: 3. The Snowball and Avalanche tabs show the payoff months for each debt under each strategy.
B10: 4. Pick the plan you'll actually stick to. Log wins on the Progress tab.
B12: COLOR LEGEND
B13: Yellow cells = yours to edit. Everything else calculates automatically.
B14: The pre-filled numbers are a realistic example — replace them with your own.
B16: Snowball = smallest balance first (fastest wins, best motivation).
B17: Avalanche = highest interest rate first (mathematically cheapest).
B19: Questions? Message us — real humans, fast replies, we'll fix anything.

Sheet My Debts
B2: MY DEBTS
B4: Monthly EXTRA payment (beyond minimums): | E4: 150
B6: Debt name | C6: Balance | D6: APR | E6: Min payment | F6: Notes
B7: Store card | C7: 640 | D7: 0.279 | E7: 35
B8: Medical bill | C8: 1200 | D8: 0 | E8: 50
B9: Credit card A | C9: 2850 | D9: 0.246 | E9: 75
B10: Credit card B | C10: 4100 | D10: 0.219 | E10: 95
B11: Car loan | C11: 9400 | D11: 0.069 | E11: 310
B17: Total | C17: =SUM(C7:C16) | E17: =SUM(E7:E16)
B19: Total monthly attack (minimums + extra): | E19: =E17+E4

Sheet Snowball
B2: SNOWBALL PLAN
B4: Smallest balance first. Extra payment attacks the top row. Update this order if your debts change.
B6: Debt (attack order) | C6: Balance | D6: APR | E6: Min payment | F6: You pay now | G6: Months to payoff*
B7: Store card | C7: 640 | D7: 0.279 | E7: 35 | F7: =E7+IF(ROW()=7,'My Debts'!$E$4,0) | G7: =IFERROR(IF(C7=0,"—",ROUNDUP(IF(D7=0,C7/F7,NPER(D7/12,-F7,C7)),0)),"raise payment")
B8: Medical bill | C8: 1200 | D8: 0 | E8: 50 | F8: =E8+IF(ROW()=7,'My Debts'!$E$4,0) | G8: =IFERROR(IF(C8=0,"—",ROUNDUP(IF(D8=0,C8/F8,NPER(D8/12,-F8,C8)),0)),"raise payment")
B9: Credit card A | C9: 2850 | D9: 0.246 | E9: 75 | F9: =E9+IF(ROW()=7,'My Debts'!$E$4,0) | G9: =IFERROR(IF(C9=0,"—",ROUNDUP(IF(D9=0,C9/F9,NPER(D9/12,-F9,C9)),0)),"raise payment")
B10: Credit card B | C10: 4100 | D10: 0.219 | E10: 95 | F10: =E10+IF(ROW()=7,'My Debts'!$E$4,0) | G10: =IFERROR(IF(C10=0,"—",ROUNDUP(IF(D10=0,C10/F10,NPER(D10/12,-F10,C10)),0)),"raise payment")
B11: Car loan | C11: 9400 | D11: 0.069 | E11: 310 | F11: =E11+IF(ROW()=7,'My Debts'!$E$4,0) | G11: =IFERROR(IF(C11=0,"—",ROUNDUP(IF(D11=0,C11/F11,NPER(D11/12,-F11,C11)),0)),"raise payment")
B13: *Months at the shown payment. When the #1 debt hits $0, roll its full payment onto the next debt — your real payoff is FASTER than shown. Zero-APR debts divide balance by payment.

Sheet Avalanche
B2: AVALANCHE PLAN
B4: Highest APR first. Extra payment attacks the top row. Update this order if your debts change.
B6: Debt (attack order) | C6: Balance | D6: APR | E6: Min payment | F6: You pay now | G6: Months to payoff*
B7: Store card | C7: 640 | D7: 0.279 | E7: 35 | F7: =E7+IF(ROW()=7,'My Debts'!$E$4,0) | G7: =IFERROR(IF(C7=0,"—",ROUNDUP(IF(D7=0,C7/F7,NPER(D7/12,-F7,C7)),0)),"raise payment")
B8: Credit card A | C8: 2850 | D8: 0.246 | E8: 75 | F8: =E8+IF(ROW()=7,'My Debts'!$E$4,0) | G8: =IFERROR(IF(C8=0,"—",ROUNDUP(IF(D8=0,C8/F8,NPER(D8/12,-F8,C8)),0)),"raise payment")
B9: Credit card B | C9: 4100 | D9: 0.219 | E9: 95 | F9: =E9+IF(ROW()=7,'My Debts'!$E$4,0) | G9: =IFERROR(IF(C9=0,"—",ROUNDUP(IF(D9=0,C9/F9,NPER(D9/12,-F9,C9)),0)),"raise payment")
B10: Car loan | C10: 9400 | D10: 0.069 | E10: 310 | F10: =E10+IF(ROW()=7,'My Debts'!$E$4,0) | G10: =IFERROR(IF(C10=0,"—",ROUNDUP(IF(D10=0,C10/F10,NPER(D10/12,-F10,C10)),0)),"raise payment")
B11: Medical bill | C11: 1200 | D11: 0 | E11: 50 | F11: =E11+IF(ROW()=7,'My Debts'!$E$4,0) | G11: =IFERROR(IF(C11=0,"—",ROUNDUP(IF(D11=0,C11/F11,NPER(D11/12,-F11,C11)),0)),"raise payment")
B13: *Months at the shown payment. When the #1 debt hits $0, roll its full payment onto the next debt — your real payoff is FASTER than shown. Zero-APR debts divide balance by payment.

Sheet Progress
B2: PROGRESS — DEBTS DESTROYED
B4: Debt | C4: Paid off (date) | D4: Amount killed | E4: How it felt
B16: Total destroyed | D16: =SUM(D5:D14)
